itunes2Spotify/__init__.py
itunes2Spotify/album.py
itunes2Spotify/itunes2spotify.py
itunes2Spotify/menu.py
itunes2Spotify/transfer.py
itunes2Spotify-0.1.0.dist-info/METADATA
itunes2Spotify-0.1.0.dist-info/RECORD
itunes2Spotify-0.1.0.dist-info/WHEEL
itunes2Spotify-0.1.0.dist-info/entry_points.txt
itunes2Spotify-0.1.0.dist-info/top_level.txt
