Metadata-Version: 2.1
Name: itunes2Spotify
Version: 0.1.0
Summary: Transfer albums from iTunes to Spotify
Home-page: https://github.com/colbymorrison/itunes2spotify
Author: Colby Morrison
Author-email: colbyamorrison@gmail.com
License: MIT
Platform: UNKNOWN
Requires-Dist: spotipy
Requires-Dist: click
